{"startTime":"2023-07-22T09:39:59.631Z","checkResult":false,"endTime":"2023-07-22T09:40:10.404Z","logs":"2023-07-22 11:40:02 [14936] INFO [conf/application/windows/sqoolctl-0.9.70] Checking that the unit needs to be performed\n2023-07-22 11:40:02 [14936] DEBUG [conf/application/windows/sqoolctl-0.9.70] Querying C:\\Program Files\\Unowhy\\HiSqool Manager\\sqoolctl\\sqoolctl.exe version...\n2023-07-22 11:40:10 [14936] DEBUG [conf/application/windows/sqoolctl-0.9.70] return code is 0\n2023-07-22 11:40:10 [14936] INFO [conf/application/windows/sqoolctl-0.9.70] Current version is 0.9.70.\n","id":1273,"name":"conf/application/windows/sqoolctl-0.9.70","description":"Installation de l'application sqoolctl 0.9.70"}